palette_generator/__init__.py
palette_generator/__main__.py
palette_generator/_make_parser.py
palette_generator/convert_colors.py
palette_generator/extract_colors.py
palette_generator/gen_palette.py
palette_generator/make_theme.py
palette_generator-0.1.4.dist-info/LICENSE.md
palette_generator-0.1.4.dist-info/METADATA
palette_generator-0.1.4.dist-info/WHEEL
palette_generator-0.1.4.dist-info/RECORD
